Metadata-Version: 1.0
Name: testvsfs
Version: 0.1.1
Summary: VSFS test example
Home-page: https://github.com/sbg/vsfs-bix-test
Author: Mladenl
Author-email: mladen.lazarevic@sbgenomics.com
License: UNKNOWN
Platform: UNKNOWN
